{"is_source_file": false, "format": "", "description": "", "external_files": [], "external_methods": [], "published": [], "classes": [], "methods": [], "calls": [], "search-terms": ["CSS variables", "theme management", "light theme", "dark theme", "responsive design", "App.css"], "state": 2, "file_id": 7, "knowledge_revision": 18, "git_revision": "26e0a8e2a17e22e7bfc2f1dce73a42f8f7028077", "hash": "22f9e17cc1848b56dbb244518ac2707e", "format-version": 4, "code-base-name": "marketplace_frontend", "filename": "marketplace_frontend/src/App.css", "revision_history": [{"18": "26e0a8e2a17e22e7bfc2f1dce73a42f8f7028077"}]}